companies_house/__init__.py
companies_house/api.py
companies_house/update.py
companies_house-0.1.2.dist-info/DESCRIPTION.rst
companies_house-0.1.2.dist-info/METADATA
companies_house-0.1.2.dist-info/RECORD
companies_house-0.1.2.dist-info/WHEEL
companies_house-0.1.2.dist-info/metadata.json
companies_house-0.1.2.dist-info/top_level.txt
