Metadata-Version: 2.0
Name: companies-house
Version: 0.1.2
Summary: Dynamic API wrapper for Companies' House
Home-page: http://previ.se
Author: Elias Mistler, Previse Limited
Author-email: elias@previ.se
License: MIT
Project-URL: Source, https://github.com/previsedigital/companies_house
Keywords: companieshouse api
Platform: UNKNOWN
Classifier: Development Status :: 3 - Alpha
Classifier: Intended Audience :: Developers
Classifier: Topic :: Software Development
Classifier: Topic :: Internet
Classifier: Topic :: Office/Business
Classifier: License :: OSI Approved :: MIT License
Classifier: Programming Language :: Python :: 3 :: Only
Requires-Python: >=3
Requires-Dist: pandas
